{
    "id": 64111,
    "group": {
        "id": "model_64111",
        "type": "kGroup",
        "count": 1,
        "count_point_id": null,
        "points": [
            {
                "id": "ID",
                "data_type": "uint16",
                "data": 64111,
                "count": 1,
                "count_point_id": null,
                "size": 1,
                "sf": 0,
                "sf_id": null,
                "units": null,
                "access": "kR",
                "mandatory": "kM",
                "label": "Model ID"
            },
            {
                "id": "L",
                "data_type": "uint16",
                "data": null,
                "count": 1,
                "count_point_id": null,
                "size": 1,
                "sf": 0,
                "sf_id": null,
                "units": null,
                "access": "kR",
                "mandatory": "kM",
                "label": "Model Length"
            },
            {
                "id": "Port",
                "data_type": "uint16",
                "data": null,
                "count": 1,
                "count_point_id": null,
                "size": 1,
                "sf": 0,
                "sf_id": null,
                "units": null,
                "access": "kR",
                "mandatory": "kM",
                "label": "Port Number"
            },
            {
                "id": "V_SF",
                "data_type": "sunssf",
                "data": null,
                "count": 1,
                "count_point_id": null,
                "size": 1,
                "sf": 0,
                "sf_id": null,
                "units": null,
                "access": "kR",
                "mandatory": "kM",
                "label": null
            },
            {
                "id": "A_SF",
                "data_type": "sunssf",
                "data": null,
                "count": 1,
                "count_point_id": null,
                "size": 1,
                "sf": 0,
                "sf_id": null,
                "units": null,
                "access": "kR",
                "mandatory": "kM",
                "label": null
            },
            {
                "id": "P_SF",
                "data_type": "sunssf",
                "data": null,
                "count": 1,
                "count_point_id": null,
                "size": 1,
                "sf": 0,
                "sf_id": null,
                "units": null,
                "access": "kR",
                "mandatory": "kM",
                "label": null
            },
            {
                "id": "AH_SF",
                "data_type": "sunssf",
                "data": null,
                "count": 1,
                "count_point_id": null,
                "size": 1,
                "sf": 0,
                "sf_id": null,
                "units": null,
                "access": "kR",
                "mandatory": "kM",
                "label": null
            },
            {
                "id": "KWH_SF",
                "data_type": "sunssf",
                "data": null,
                "count": 1,
                "count_point_id": null,
                "size": 1,
                "sf": 0,
                "sf_id": null,
                "units": null,
                "access": "kR",
                "mandatory": "kM",
                "label": null
            },
            {
                "id": "BattV",
                "data_type": "uint16",
                "data": null,
                "count": 1,
                "count_point_id": null,
                "size": 1,
                "sf": 0,
                "sf_id": "V_SF",
                "units": "V",
                "access": "kR",
                "mandatory": "kM",
                "label": "Battery Voltage"
            },
            {
                "id": "ArrayV",
                "data_type": "uint16",
                "data": null,
                "count": 1,
                "count_point_id": null,
                "size": 1,
                "sf": 0,
                "sf_id": "V_SF",
                "units": "V",
                "access": "kR",
                "mandatory": "kM",
                "label": "Array Voltage"
            },
            {
                "id": "OutputA",
                "data_type": "uint16",
                "data": null,
                "count": 1,
                "count_point_id": null,
                "size": 1,
                "sf": 0,
                "sf_id": "A_SF",
                "units": "A",
                "access": "kR",
                "mandatory": "kM",
                "label": "Output Current"
            },
            {
                "id": "InputA",
                "data_type": "uint16",
                "data": null,
                "count": 1,
                "count_point_id": null,
                "size": 1,
                "sf": 0,
                "sf_id": "P_SF",
                "units": "A",
                "access": "kR",
                "mandatory": "kM",
                "label": "Array Current"
            },
            {
                "id": "ChargerSt",
                "data_type": "enum16",
                "data": null,
                "count": 1,
                "count_point_id": null,
                "size": 1,
                "sf": 0,
                "sf_id": null,
                "units": null,
                "access": "kR",
                "mandatory": "kM",
                "label": "Operating State"
            },
            {
                "id": "OutputW",
                "data_type": "uint16",
                "data": null,
                "count": 1,
                "count_point_id": null,
                "size": 1,
                "sf": 0,
                "sf_id": "P_SF",
                "units": "W",
                "access": "kR",
                "mandatory": "kM",
                "label": "Output Wattage"
            },
            {
                "id": "TodayMinBatV",
                "data_type": "uint16",
                "data": null,
                "count": 1,
                "count_point_id": null,
                "size": 1,
                "sf": 0,
                "sf_id": "V_SF",
                "units": "V",
                "access": "kR",
                "mandatory": "kM",
                "label": "Today's Minimum Battery Voltage"
            },
            {
                "id": "TodayMaxBatV",
                "data_type": "uint16",
                "data": null,
                "count": 1,
                "count_point_id": null,
                "size": 1,
                "sf": 0,
                "sf_id": "V_SF",
                "units": "V",
                "access": "kR",
                "mandatory": "kM",
                "label": "Today's Maximum Battery Voltage"
            },
            {
                "id": "VOCV",
                "data_type": "uint16",
                "data": null,
                "count": 1,
                "count_point_id": null,
                "size": 1,
                "sf": 0,
                "sf_id": "V_SF",
                "units": "V",
                "access": "kR",
                "mandatory": "kM",
                "label": "VOC"
            },
            {
                "id": "TodayMaxVOC",
                "data_type": "uint16",
                "data": null,
                "count": 1,
                "count_point_id": null,
                "size": 1,
                "sf": 0,
                "sf_id": "V_SF",
                "units": "V",
                "access": "kR",
                "mandatory": "kM",
                "label": "Today's Maximum VOC"
            },
            {
                "id": "TodaykWhOutput",
                "data_type": "uint16",
                "data": null,
                "count": 1,
                "count_point_id": null,
                "size": 1,
                "sf": 0,
                "sf_id": "KWH_SF",
                "units": "kWh",
                "access": "kR",
                "mandatory": "kM",
                "label": "Today's kWh"
            },
            {
                "id": "TodayAHOutput",
                "data_type": "uint16",
                "data": null,
                "count": 1,
                "count_point_id": null,
                "size": 1,
                "sf": 0,
                "sf_id": "AH_SF",
                "units": "AH",
                "access": "kR",
                "mandatory": "kM",
                "label": "Today's AH"
            },
            {
                "id": "LifeTimeKWHOut",
                "data_type": "uint16",
                "data": null,
                "count": 1,
                "count_point_id": null,
                "size": 1,
                "sf": 0,
                "sf_id": "P_SF",
                "units": "kWh",
                "access": "kR",
                "mandatory": "kM",
                "label": "Lifetime kWh"
            },
            {
                "id": "LifeTimeAHOut",
                "data_type": "uint16",
                "data": null,
                "count": 1,
                "count_point_id": null,
                "size": 1,
                "sf": 0,
                "sf_id": "KWH_SF",
                "units": "kAH",
                "access": "kR",
                "mandatory": "kM",
                "label": "Lifetime kAH"
            },
            {
                "id": "LifeTimeMaxOut",
                "data_type": "uint16",
                "data": null,
                "count": 1,
                "count_point_id": null,
                "size": 1,
                "sf": 0,
                "sf_id": "P_SF",
                "units": "W",
                "access": "kR",
                "mandatory": "kM",
                "label": "Lifetime Maximum Output Wattage"
            },
            {
                "id": "LifeTimeMaxBatt",
                "data_type": "uint16",
                "data": null,
                "count": 1,
                "count_point_id": null,
                "size": 1,
                "sf": 0,
                "sf_id": "V_SF",
                "units": "V",
                "access": "kR",
                "mandatory": "kM",
                "label": "Lifetime Maximum Battery Voltage"
            },
            {
                "id": "LifeTimeMaxVOC",
                "data_type": "uint16",
                "data": null,
                "count": 1,
                "count_point_id": null,
                "size": 1,
                "sf": 0,
                "sf_id": "V_SF",
                "units": "V",
                "access": "kR",
                "mandatory": "kM",
                "label": "Lifetime Maximum VOC Voltage"
            }
        ],
        "groups": [],
        "label": "Basic Charge Controller"
    }
}