{
    "id": 306,
    "group": {
        "id": "ref_point",
        "type": "kGroup",
        "count": 1,
        "count_point_id": null,
        "points": [
            {
                "id": "ID",
                "data_type": "uint16",
                "data": 306,
                "count": 1,
                "count_point_id": null,
                "size": 1,
                "sf": 0,
                "sf_id": null,
                "units": null,
                "access": "kR",
                "mandatory": "kM",
                "label": "Model ID"
            },
            {
                "id": "L",
                "data_type": "uint16",
                "data": null,
                "count": 1,
                "count_point_id": null,
                "size": 1,
                "sf": 0,
                "sf_id": null,
                "units": null,
                "access": "kR",
                "mandatory": "kM",
                "label": "Model Length"
            },
            {
                "id": "GHI",
                "data_type": "uint16",
                "data": null,
                "count": 1,
                "count_point_id": null,
                "size": 1,
                "sf": 0,
                "sf_id": null,
                "units": "W/m2",
                "access": "kR",
                "mandatory": "kO",
                "label": "GHI"
            },
            {
                "id": "A",
                "data_type": "uint16",
                "data": null,
                "count": 1,
                "count_point_id": null,
                "size": 1,
                "sf": 0,
                "sf_id": null,
                "units": "W/m2",
                "access": "kR",
                "mandatory": "kO",
                "label": "Amps"
            },
            {
                "id": "V",
                "data_type": "uint16",
                "data": null,
                "count": 1,
                "count_point_id": null,
                "size": 1,
                "sf": 0,
                "sf_id": null,
                "units": "W/m2",
                "access": "kR",
                "mandatory": "kO",
                "label": "Voltage"
            },
            {
                "id": "Tmp",
                "data_type": "uint16",
                "data": null,
                "count": 1,
                "count_point_id": null,
                "size": 1,
                "sf": 0,
                "sf_id": null,
                "units": "W/m2",
                "access": "kR",
                "mandatory": "kO",
                "label": "Temperature"
            }
        ],
        "groups": [],
        "label": "Reference Point Model"
    }
}